deepethogram/__init__.py
deepethogram/__main__.py
deepethogram/base.py
deepethogram/callbacks.py
deepethogram/configuration.py
deepethogram/debug.py
deepethogram/file_io.py
deepethogram/losses.py
deepethogram/metrics.py
deepethogram/postprocessing.py
deepethogram/projects.py
deepethogram/schedulers.py
deepethogram/stoppers.py
deepethogram/utils.py
deepethogram/viz.py
deepethogram/zscore.py
deepethogram/conf/__init__.py
deepethogram/conf/augs.yaml
deepethogram/conf/config.yaml
deepethogram/conf/debug.yaml
deepethogram/conf/gui.yaml
deepethogram/conf/inference.yaml
deepethogram/conf/postprocessor.yaml
deepethogram/conf/train.yaml
deepethogram/conf/zscore.yaml
deepethogram/conf/model/feature_extractor.yaml
deepethogram/conf/model/flow_generator.yaml
deepethogram/conf/model/sequence.yaml
deepethogram/conf/preset/deg_f.yaml
deepethogram/conf/preset/deg_m.yaml
deepethogram/conf/preset/deg_s.yaml
deepethogram/conf/project/project_config_default.yaml
deepethogram/conf/tune/feature_extractor.yaml
deepethogram/conf/tune/sequence.yaml
deepethogram/conf/tune/tune.yaml
deepethogram/data/__init__.py
deepethogram/data/augs.py
deepethogram/data/dali.py
deepethogram/data/dataloaders.py
deepethogram/data/datasets.py
deepethogram/data/keypoint_utils.py
deepethogram/data/utils.py
deepethogram/feature_extractor/__init__.py
deepethogram/feature_extractor/__main__.py
deepethogram/feature_extractor/inference.py
deepethogram/feature_extractor/losses.py
deepethogram/feature_extractor/train.py
deepethogram/feature_extractor/models/CNN.py
deepethogram/feature_extractor/models/__init__.py
deepethogram/feature_extractor/models/hidden_two_stream.py
deepethogram/feature_extractor/models/utils.py
deepethogram/feature_extractor/models/classifiers/__init__.py
deepethogram/feature_extractor/models/classifiers/alexnet.py
deepethogram/feature_extractor/models/classifiers/densenet.py
deepethogram/feature_extractor/models/classifiers/inception.py
deepethogram-0.1.4.dist-info/METADATA
deepethogram-0.1.4.dist-info/WHEEL
deepethogram-0.1.4.dist-info/entry_points.txt
deepethogram-0.1.4.dist-info/top_level.txt
deepethogram-0.1.4.dist-info/RECORD
