Metadata-Version: 2.1
Name: deepethogram
Version: 0.1.4
Summary: Temporal action detection for biology
Author: Jim Bohnslav
Author-email: jbohnslav@gmail.com
Classifier: Programming Language :: Python :: 3
Classifier: Operating System :: OS Independent
Requires-Python: >=3.6
Requires-Dist: chardet (<4.0)
Requires-Dist: h5py
Requires-Dist: kornia (>=0.5)
Requires-Dist: matplotlib
Requires-Dist: numpy
Requires-Dist: omegaconf (>=2)
Requires-Dist: opencv-python-headless
Requires-Dist: opencv-transforms
Requires-Dist: pandas (<1.4)
Requires-Dist: PySide2
Requires-Dist: scikit-learn (<1.1)
Requires-Dist: scipy (<1.8)
Requires-Dist: tqdm
Requires-Dist: vidio
Requires-Dist: pytorch-lightning (>=1.5.10)
